yoomoney_async/__init__.py
yoomoney_async/client.py
yoomoney_async/exceptions.py
yoomoney_async/setup.py
yoomoney_async/account/__init__.py
yoomoney_async/account/account.py
yoomoney_async/account/balance_details.py
yoomoney_async/account/card.py
yoomoney_async/authorize/__init__.py
yoomoney_async/authorize/authorize.py
yoomoney_async/history/__init__.py
yoomoney_async/history/exceptions.py
yoomoney_async/history/history.py
yoomoney_async/operation/__init__.py
yoomoney_async/operation/operation.py
yoomoney_async/operation_details/__init__.py
yoomoney_async/operation_details/digital_bonus.py
yoomoney_async/operation_details/digital_good.py
yoomoney_async/operation_details/digital_product.py
yoomoney_async/operation_details/operation_details.py
yoomoney_async/quickpay/__init__.py
yoomoney_async/quickpay/quickpay.py
YooMoney_async-0.0.6.dist-info/METADATA
YooMoney_async-0.0.6.dist-info/WHEEL
YooMoney_async-0.0.6.dist-info/top_level.txt
YooMoney_async-0.0.6.dist-info/RECORD
