Metadata-Version: 2.1
Name: YooMoney-async
Version: 0.0.6
Summary: Unofficial YooMoney_async API python library
Home-page: https://github.com/Navigatoroleg/yoomoney_asunc.git
Author: OlesMokovoz
Author-email: oleg-oleg-2023@mail.ru
